LICENSE
README.md
setup.cfg
setup.py
pm2py/__init__.py
pm2py/__main__.py
pm2py.egg-info/PKG-INFO
pm2py.egg-info/SOURCES.txt
pm2py.egg-info/dependency_links.txt
pm2py.egg-info/requires.txt
pm2py.egg-info/top_level.txt