Metadata-Version: 2.1
Name: pm2py
Version: 1.0.0
Summary: PM2 wrapper for Python
Home-page: https://github.com/yusufusta/pm2py
Author: Yusuf Usta
Author-email: yusuf@usta.email
Maintainer: Yusuf Usta
Maintainer-email: yusuf@usta.email
License: GPL3
Keywords: pm2,node
Platform: UNKNOWN
Classifier: Intended Audience :: Developers
Classifier: License :: OSI Approved :: GNU General Public License v3 (GPLv3)
Classifier: Programming Language :: Python :: 3.6
Classifier: Programming Language :: Python :: 3.7
Classifier: Programming Language :: Python :: 3.8
Classifier: Programming Language :: Python :: 3.9
Classifier: Programming Language :: Python :: 3.10
License-File: LICENSE
